nba_bbref_webscrape/__init__.py
nba_bbref_webscrape/aws_functions.py
nba_bbref_webscrape/boxscores_functions.py
nba_bbref_webscrape/gambling_odds_functions.py
nba_bbref_webscrape/injuries_functions.py
nba_bbref_webscrape/opp_stats_functions.py
nba_bbref_webscrape/play_by_play_functions.py
nba_bbref_webscrape/player_adv_stats_functions.py
nba_bbref_webscrape/player_shooting_stats_functions.py
nba_bbref_webscrape/player_stats_functions.py
nba_bbref_webscrape/postgresql_functions.py
nba_bbref_webscrape/reddit_functions.py
nba_bbref_webscrape/schedule_functions.py
nba_bbref_webscrape/schema.py
nba_bbref_webscrape/transactions_functions.py
nba_bbref_webscrape/twitter_functions.py
nba_bbref_webscrape/utils.py
nba_bbref_webscrape-0.0.6.dist-info/WHEEL
nba_bbref_webscrape-0.0.6.dist-info/METADATA
nba_bbref_webscrape-0.0.6.dist-info/RECORD
